adam_io/__init__.py
adam_io/adam.py
adam_io/digital_io.py
adam_io/requestor.py
adam_io/utils.py
test/__init__.py
test/test_adam.py
adam_io-2.1608646378.6553204.dist-info/LICENSE
adam_io-2.1608646378.6553204.dist-info/METADATA
adam_io-2.1608646378.6553204.dist-info/WHEEL
adam_io-2.1608646378.6553204.dist-info/top_level.txt
adam_io-2.1608646378.6553204.dist-info/RECORD
