Metadata-Version: 2.1
Name: adam-io
Version: 2.1608646378.6553204
Summary: ADAM 6050-D REST API Python Wrapper
Home-page: https://adam-io.readthedocs.io/
Author: Kemal Çelikel
Author-email: kcelikel@eventgates.com
License: UNKNOWN
Platform: UNKNOWN
Classifier: Programming Language :: Python :: 3
Classifier: License :: OSI Approved :: MIT License
Classifier: Operating System :: OS Independent
Requires-Python: >=3.6
